timeturner/__init__.py
timeturner/db.py
timeturner/helper.py
timeturner/loader.py
timeturner/models.py
timeturner/parser.py
timeturner/rich_output.py
timeturner/run.py
timeturner/settings.py
timeturner/timeturner.py
timeturner/tools/boltons_iterutils.py
timeturner-0.6.0.dist-info/METADATA
timeturner-0.6.0.dist-info/WHEEL
timeturner-0.6.0.dist-info/entry_points.txt
timeturner-0.6.0.dist-info/licenses/LICENSE
timeturner-0.6.0.dist-info/RECORD
