Metadata-Version: 2.4
Name: timeturner
Version: 0.6.0
Author-email: Olaf Gladis <olaf@gladis.org>
License-File: LICENSE
Requires-Python: ~=3.10
Requires-Dist: pydantic<2,>=1.10.5
Requires-Dist: rich
Requires-Dist: tomlkit<0.12,>=0.11.6
Requires-Dist: typer-slim[standard]
